{"rates":{"btc":{"name":"Bitcoin","unit":"BTC","value":1.0,"type":"crypto"},"eth":{"name":"Ether","unit":"ETH","value":13.495,"type":"crypto"},"ltc":{"name":"Litecoin","unit":"LTC","value":222.53,"type":"crypto"},"bch":{"name":"Bitcoin Cash","unit":"BCH","value":157.699,"type":"crypto"},"bnb":{"name":"Binance Coin","unit":"BNB","value":59.245,"type":"crypto"},"eos":{"name":"EOS","unit":"EOS","value":16544.133,"type":"crypto"},"xrp":{"name":"XRP","unit":"XRP","value":44334.711,"type":"crypto"},"xlm":{"name":"Lumens","unit":"XLM","value":201014.778,"type":"crypto"},"link":{"name":"Chainlink","unit":"LINK","value":2491.459,"type":"crypto"},"dot":{"name":"Polkadot","unit":"DOT","value":3252.723,"type":"crypto"},"yfi":{"name":"Yearn.finance","unit":"YFI","value":2.468,"type":"crypto"},"usd":{"name":"US Dollar","unit":"$","value":17173.769,"type":"fiat"},"aed":{"name":"United Arab Emirates Dirham","unit":"DH","value":63080.974,"type":"fiat"},"ars":{"name":"Argentine Peso","unit":"$","value":2918309.776,"type":"fiat"},"aud":{"name":"Australian Dollar","unit":"A$","value":25266.685,"type":"fiat"},"bdt":{"name":"Bangladeshi Taka","unit":"৳","value":1776146.949,"type":"fiat"},"bhd":{"name":"Bahraini Dinar","unit":"BD","value":6464.687,"type":"fiat"},"bmd":{"name":"Bermudian Dollar","unit":"$","value":17173.769,"type":"fiat"},"brl":{"name":"Brazil Real","unit":"R$","value":89956.206,"type":"fiat"},"cad":{"name":"Canadian Dollar","unit":"CA$","value":23575.292,"type":"fiat"},"chf":{"name":"Swiss Franc","unit":"Fr.","value":16059.209,"type":"fiat"},"clp":{"name":"Chilean Peso","unit":"CLP$","value":14705837.4,"type":"fiat"},"cny":{"name":"Chinese Yuan","unit":"¥","value":119489.938,"type":"fiat"},"czk":{"name":"Czech Koruna","unit":"Kč","value":395719.722,"type":"fiat"},"dkk":{"name":"Danish Krone","unit":"kr.","value":121281.162,"type":"fiat"},"eur":{"name":"Euro","unit":"€","value":16291.587,"type":"fiat"},"gbp":{"name":"British Pound Sterling","unit":"£","value":14009.966,"type":"fiat"},"hkd":{"name":"Hong Kong Dollar","unit":"HK$","value":133715.83,"type":"fiat"},"huf":{"name":"Hungarian Forint","unit":"Ft","value":6825199.622,"type":"fiat"},"idr":{"name":"Indonesian Rupiah","unit":"Rp","value":267962331.294,"type":"fiat"},"ils":{"name":"Israeli New Shekel","unit":"₪","value":58851.486,"type":"fiat"},"inr":{"name":"Indian Rupee","unit":"₹","value":1415825.337,"type":"fiat"},"jpy":{"name":"Japanese Yen","unit":"¥","value":2345507.41,"type":"fiat"},"krw":{"name":"South Korean Won","unit":"₩","value":22399232.829,"type":"fiat"},"kwd":{"name":"Kuwaiti Dinar","unit":"KD","value":5268.586,"type":"fiat"},"lkr":{"name":"Sri Lankan Rupee","unit":"Rs","value":6315765.465,"type":"fiat"},"mmk":{"name":"Burmese Kyat","unit":"K","value":36090081.075,"type":"fiat"},"mxn":{"name":"Mexican Peso","unit":"MX$","value":339645.646,"type":"fiat"},"myr":{"name":"Malaysian Ringgit","unit":"RM","value":75624.695,"type":"fiat"},"ngn":{"name":"Nigerian Naira","unit":"₦","value":7621820.582,"type":"fiat"},"nok":{"name":"Norwegian Krone","unit":"kr","value":171830.437,"type":"fiat"},"nzd":{"name":"New Zealand Dollar","unit":"NZ$","value":26779.626,"type":"fiat"},"php":{"name":"Philippine Peso","unit":"₱","value":950997.489,"type":"fiat"},"pkr":{"name":"Pakistani Rupee","unit":"₨","value":3861636.0,"type":"fiat"},"pln":{"name":"Polish Zloty","unit":"zł","value":76467.069,"type":"fiat"},"rub":{"name":"Russian Ruble","unit":"₽","value":1073618.257,"type":"fiat"},"sar":{"name":"Saudi Riyal","unit":"SR","value":64575.143,"type":"fiat"},"sek":{"name":"Swedish Krona","unit":"kr","value":177751.094,"type":"fiat"},"sgd":{"name":"Singapore Dollar","unit":"S$","value":23287.631,"type":"fiat"},"thb":{"name":"Thai Baht","unit":"฿","value":594637.608,"type":"fiat"},"try":{"name":"Turkish Lira","unit":"₺","value":320356.068,"type":"fiat"},"twd":{"name":"New Taiwan Dollar","unit":"NT$","value":527384.146,"type":"fiat"},"uah":{"name":"Ukrainian hryvnia","unit":"₴","value":631489.633,"type":"fiat"},"vef":{"name":"Venezuelan bolívar fuerte","unit":"Bs.F","value":1719.609,"type":"fiat"},"vnd":{"name":"Vietnamese đồng","unit":"₫","value":408735722.926,"type":"fiat"},"zar":{"name":"South African Rand","unit":"R","value":298040.3,"type":"fiat"},"xdr":{"name":"IMF Special Drawing Rights","unit":"XDR","value":12966.831,"type":"fiat"},"xag":{"name":"Silver - Troy Ounce","unit":"XAG","value":731.421,"type":"commodity"},"xau":{"name":"Gold - Troy Ounce","unit":"XAU","value":9.555,"type":"commodity"},"bits":{"name":"Bits","unit":"μBTC","value":1000000.0,"type":"crypto"},"sats":{"name":"Satoshi","unit":"sats","value":100000000.0,"type":"crypto"}}}
